{
  "acdc/166": "Fusaka（當時的下一次以太坊升級）測試網進展、Holesky 測試鏈的分叉狀態，以及各功能提案的時間規劃。",
  "acdc/167": "敲定 Fusaka 升級主網上線時間，並確認驗證者信任支付（Trusted Payments）的處理規則。",
  "acdc/168": "確認 Fusaka 主網上線時程，以及後續開發方向的規劃討論。",
  "acdc/169": "Fusaka 即將啟用前的準備狀況確認，以及技術規格文件的整理方式。",
  "acdc/170": "即將上線功能的最後確認，以及修正幾個在測試中發現的技術問題。",
  "acdc/171": "網路運行狀況回顧，並開始規劃 Fusaka 之後的下一次大型升級 Glamsterdam 的方向。",
  "acdc/172": "Glamsterdam 升級的規劃進展，確認納入「Sparse Blob Pool」——有助於降低節點在傳輸大量 Blob 資料時的負擔。",
  "acdc/173": "Fusaka 各項功能提案（EIP）的開發進度更新，開發網路（DevNet0）規格正式凍結、準備發布。",
  "acdc/174": "以太坊狀態樹底層改造（Verkle Tries 相關）的實作進展，以及確保新技術不破壞既有功能的相容性討論。",
  "acdc/175": "確認「強制交易包含清單（FOCIL，防止驗證者審查交易）」為 Hegotá 升級的重點功能，並討論其他技術進展與展示計畫。",
  "acdc/176": "決定修正PTC（防止驗證者審查交易的機制）並在4月中旬推出Glamsterdam DevNet 0測試網，確保以太坊升級進展順利",
  "acde/221": "確認測試網啟動時間表，以及幾項新功能是否納入升級的決策。",
  "acde/222": "確認 Fusaka 升級主網啟動時程，以及各客戶端的開發進度更新。",
  "acde/223": "Fusaka 時間規劃確認，以及 Holesky 測試網遷移計畫的安排。",
  "acde/224": "Fusaka 主網上線的最終計畫確認，以及待解決技術問題的討論。",
  "acde/225": "Fusaka 升級成功上線後的狀態回顧——網路參與度已恢復，並開始規劃後續調整方向。",
  "acde/226": "開始規劃下一次升級 Hegotá 的功能清單與時間表，決定哪些提案可以納入考慮。",
  "acde/227": "多個功能提案的進度更新，其中「限制合約大小」和「控制狀態增長」兩項決策暫緩。",
  "acde/228": "開發進度更新——測試網啟動延遲，以及幾項功能提案的納入決策。",
  "acde/229": "即將推出的開發測試網規劃，提案截止日期確認，以及幾項技術優化的決策。",
  "acde/230": "Glamsterdam 升級各項功能提案的進度更新，以及幾個技術問題的解決情況。",
  "acde/231": "Hegotá 升級的功能決策時程延後兩週，同時測試了部分雲端基礎設施功能。",
  "acde/232": "Glamsterdam（以太坊下一次大型升級）的開發進展，確認了哪些新功能提案獲得採納、哪些被拒絕。",
  "acde/233": "Hegotá不選擇Frame交易（提升交易效率）為主題，並且未選擇El頭條，優先推AA作為非頭條主題",
  "acdt/053": "Fusaka 開發網路測試進展，以及節點參與度下滑問題的應對——並決定限制某些可能影響測試的交易操作。",
  "acdt/054": "測試網最新進度，以及確認程式碼凍結和各客戶端正式版發布的時間表——升級前的最後準備階段。",
  "acdt/055": "Holešky 測試網的啟用時間確認，以及決定暫緩主網「影子分叉」測試（平行模擬升級的測試手法）。",
  "acdt/056": "Fusaka 升級上線後的運行狀況回顧，以及依據實際表現提出的技術調整建議。",
  "acdt/057": "升級進度更新，確認即將進行的測試計畫，以及修改升級版本命名的決策。",
  "acdt/058": "硬分叉（正式升級）準備進度、驗證者支付機制的決策，以及改善測試團隊之間溝通協調的方式。",
  "acdt/059": "測試進度更新，確認新版本啟用計畫，以及網路資源限制（Gas Limit 等）的相關決策。",
  "acdt/060": "升級整體進度更新，處理測試中發現的問題，以及確定主網正式升級的時間點。",
  "acdt/061": "Hoodi 測試網成功啟用；同時決定延後「區塊存取清單（BAL）」功能的開發網測試，並取消部分後續會議。",
  "acdt/062": "Fusaka 主網升級的準備進度，以及未來版本對網路資源使用量（Gas 目標）的決策討論。",
  "acdt/063": "Fusaka 主網升級成功後的狀態確認，以及接下來要測試哪些新功能的決策。",
  "acdt/064": "升級進度與版本命名調整的討論，以及近期重要事件的回顧與後續計畫。",
  "acdt/065": "BPO3（擴大每個區塊可攜帶的資料量）的開發與測試計畫，決定即使使用需求尚低仍繼續推進。",
  "acdt/066": "開發進度確認，決定哪些新功能可如期納入、哪些需要延後處理。",
  "acdt/067": "測試網進展更新，以及決定簡化部分功能的實作方式——降低複雜度以加快推進。",
  "acdt/068": "新測試網啟動情況，以及修正幾個在測試中發現的技術問題。",
  "acdt/069": "處理測試網遇到的問題，決定暫時調低 Gas Limit（每個區塊的處理上限）以利測試進行。",
  "acdt/070": "測試網穩定性狀況確認，以及為未來版本規劃的安全防護機制討論。",
  "acdt/071": "新功能測試進展，以及確定下個版本中各操作的 Gas 費用計算方式。",
  "acdt/072": "測試環境架構調整（讓不同功能可以更獨立地測試），以及接下來測試計畫的安排。",
  "acdt/073": "優化節點間的資料傳輸效率，並決定讓部分功能改為可選擇性啟用，提升網路彈性。",
  "acdt/074": "以太坊將逐步推出測試網，並由Acd決定部分升級（EIPs）是否獲得獎勵激勵（SFI）資格",
  "acdt/075": "決定用穩定版本取代不穩定分支，並調整存儲3個epoch（區塊鏈中的一段時間）的共識資料。",
  "awd/038": "錢包相關標準草案的更新進度，以及錢包開發標準的治理架構調整計畫。",
  "bal/001": "透過「區塊存取清單（BAL）」預先標記交易會讀取的資料，讓節點提前準備、加快處理速度的方案討論。",
  "bal/002": "討論是否讓存取清單同時記錄交易索引，但決定暫不調整現有規範，等後續分析結果再決定。",
  "bal/003": "調整交易資料的儲存結構以提升處理效率，以及相關格式的決策討論。",
  "bal/004": "確定區塊存取清單（BAL）與內建合約（Precompiles）的整合方式，讓兩者能夠相互配合運作。",
  "bal/005": "討論當交易手續費為零（零小費交易）時，如何在區塊層級正確計算驗證者獎勵。",
  "bal/006": "驗證者提款的追蹤機制問題、Gas 費用調整，以及相關測試計畫的決策。",
  "bal/007": "改善節點快速同步（Snap Sync）過程中的資料管理方式，以及更完善的錯誤記錄機制。",
  "bal/008": "優化合約讀寫以太坊狀態時的驗證流程，並解決不同客戶端之間的技術不一致問題。",
  "bal/009": "決定將存取清單從區塊標頭移至執行負載（Execution Payload），並將資料保留期設定為約 15.7 天。",
  "bal/011": "測試流程優化進展，以及下個版本功能清單的決策討論。",
  "bal/012": "效能優化成果，以及共識規則的微調——讓網路更穩定、處理更有效率。",
  "bal/013": "Besu 和 Geth 兩個主流客戶端的效能優化進度，以及正式測試前的準備工作。",
  "epbs/021": "調整 ePBS（區塊提案與建構分離機制）的資料結構設計，移除部分冗餘承諾，並修正區塊提議者的驗證邏輯。",
  "epbs/023": "更新執行負載（Execution Payload）的規格，以配合 ePBS 的設計需求。",
  "epbs/024": "ePBS 規格的版本發布計畫，以及解決目前已知技術問題的決策。",
  "epbs/025": "ePBS 首個開發測試網（DevNet0）的規格正式凍結，以及簡化測試範圍以加快推進。",
  "epbs/026": "共識規範的更新，以及解決 ePBS 相關功能的命名歧義，讓各客戶端的實作能夠對齊。",
  "epbs/028": "共識規範更新，以及處理 Fusaka 升級造成的連帶影響——部分客戶端進度受影響。",
  "epbs/029": "ePBS 的長期發展方向討論，以及簡化「建設者競標出價」流程的決策——讓出塊競標機制更輕量。",
  "etm/000": "加密交易池（Mempool）的初步構想討論——讓使用者的交易在未被納入區塊前保持隱私，防止搶先交易（Front-running）攻擊。",
  "etm/001": "提出全新的 Mempool 加密架構，取代舊方案——新設計在工程實作上更可行。",
  "etm/002": "討論提升交易背後效率與安全的技術方案，並決定採用EIP-8184來改善以太坊的交易處理。",
  "focil/019": "FOCIL（強制交易包含清單）功能規格的完善進度，實驗性程式分支的開發，以及確保不同執行層客戶端能夠互通。",
  "focil/020": "處理在區塊提案流程中發現的 FOCIL 相關問題，並提出對應解決方案。",
  "focil/021": "改進「強制包含清單」的傳遞機制，讓需要強制納入的交易能更可靠地被處理。",
  "focil/022": "FOCIL 的測試進展、錯誤修復，以及後續版本的開發規劃。",
  "focil/025": "FOCIL 即將納入 Heka/Bogotá 升級的相關準備，以及未來提案流程的安排。",
  "focil/027": "FOCIL 提案進度的公開更新，技術規範的最新調整，以及測試計畫的安排。",
  "focil/028": "確認「強制交易包含清單」的使用規則，以及如何驗證節點是否正確遵守包含義務。",
  "focil/029": "FOCIL 在 Hegotá 升級中的實作進展，以及新增的驗證條件——確保節點正確執行強制包含規則。",
  "focil/030": "各以太坊客戶端實作「強制交易包含清單」的進度——此功能可防止驗證者刻意屏蔽使用者的交易。",
  "focil/031": "以太坊開發團隊正推進Besu和Lodestar的整合與優化，以提升跨鏈互操作性與系統效率",
  "pqi/028": "後量子互通性的測試準備進度，以及密碼學規範的調整決策。",
  "pqi/029": "確認不同客戶端在後量子簽名上的互通性測試進展，以及驗證者密鑰管理的未來方向。",
  "pqi/030": "針對未來量子電腦威脅的防禦準備——確立驗證者採用統一後量子簽名格式的規範。",
  "pqi/033": "更新了Devnet-3的簽名驗證方式，解決長時間運行測試網的同步問題，並加入了驗證委員會的績效指標。",
  "pqts/001": "決定以「帳戶抽象（Account Abstraction）」為基礎，支援多種量子安全簽名方案——讓使用者的錢包在量子時代仍能安全使用。",
  "pqts/003": "量子安全交易簽名的技術選型進展，以及確定優先開發哪種密碼學方案。",
  "pqts/004": "採用帳戶抽象（Account Abstraction）進行每筆交易的簽名輪換，縮短攻擊窗口並提升安全性",
  "price/001": "Glamsterdam 升級中 EVM 操作碼重新定價的方案討論——調整各操作的 Gas 費用，使其更符合實際計算成本。",
  "price/002": "確定各操作碼 Gas 費用的調整幅度，以及相關技術規範的最終決策。",
  "price/003": "透過重新定價 EVM 操作碼提升效率——讓昂貴但快速的操作能反映真實成本，減少資源浪費。",
  "price/004": "決定先收取常規燃料費用再收狀態燃料費用，並以下一版測試規範為DevNet 3的基準，暫緩其他變更",
  "rpc/020": "清理過時的 JSON-RPC API 提案，推進版本更新，並評估移除不再需要的功能。",
  "rpc/021": "JSON-RPC API（錢包與應用程式讀取以太坊資料的介面）新版本的功能清單決策。",
  "rpc/022": "統一 JSON-RPC 的錯誤回傳代碼，以及批准新增查詢合約儲存值的 API 功能。",
  "rpc/023": "FCR（快速確認機制）將大幅縮短以太坊區塊確認時間至13秒，提升交易速度與安全性",
  "tli/002": "簡化以太坊事件日誌的索引方式——讓應用程式查詢歷史事件（如轉帳記錄）更快速，且不需信任第三方索引服務。",
  "tli/003": "討論日誌索引表的建立方式，以及在控制索引資料大小的同時保持歷史查詢效率。",
  "zkevm/001": "在 Glamsterdam 升級中引入「可選 ZK 證明」的決策，以及標準化執行見證（Execution Witness）的格式，確保各客戶端對此有共識。",
  "zkevm/002": "讓以太坊支援 ZK 證明技術的執行環境規格討論，確認需相容 64 位元運算以利未來 L2 整合。"
}